genoml/__init__.py
genoml/__main__.py
genoml/dependencies.py
genoml/utils.py
genoml/cli/__init__.py
genoml/cli/continuous_supervised_test.py
genoml/cli/continuous_supervised_train.py
genoml/cli/continuous_supervised_tune.py
genoml/cli/discrete_supervised_test.py
genoml/cli/discrete_supervised_train.py
genoml/cli/discrete_supervised_tune.py
genoml/cli/harmonizing.py
genoml/cli/munging.py
genoml/continuous/__init__.py
genoml/continuous/supervised/__init__.py
genoml/continuous/supervised/testing.py
genoml/continuous/supervised/training.py
genoml/continuous/supervised/tuning.py
genoml/discrete/__init__.py
genoml/discrete/supervised/__init__.py
genoml/discrete/supervised/testing.py
genoml/discrete/supervised/training.py
genoml/discrete/supervised/tuning.py
genoml/misc/descriptions.json
genoml/preprocessing/__init__.py
genoml/preprocessing/adjuster.py
genoml/preprocessing/featureselection.py
genoml/preprocessing/harmonizing.py
genoml/preprocessing/munging.py
genoml/preprocessing/vif.py
genoml2-1.0.0b11.dist-info/LICENSE
genoml2-1.0.0b11.dist-info/METADATA
genoml2-1.0.0b11.dist-info/WHEEL
genoml2-1.0.0b11.dist-info/entry_points.txt
genoml2-1.0.0b11.dist-info/top_level.txt
genoml2-1.0.0b11.dist-info/RECORD
