Metadata-Version: 2.1
Name: genoml2
Version: 1.0.0b11
Summary: GenoML is an automated machine learning tool that optimizes basic machine learning pipelines for genomic data.
Home-page: https://genoml.github.io/
Maintainer: The GenoML Development Team
Maintainer-email: genoml@googlegroups.com
License: UNKNOWN
Download-URL: https://github.com/GenoML/genoml2/archive/v1.0.0-beta.11.tar.gz
Platform: UNKNOWN
Classifier: Development Status :: 4 - Beta
Classifier: Programming Language :: Python :: 3.6
Classifier: License :: OSI Approved :: Apache Software License
Classifier: Operating System :: OS Independent
Requires-Python: >=3.6
Requires-Dist: joblib
Requires-Dist: matplotlib
Requires-Dist: numpy
Requires-Dist: tables
Requires-Dist: pandas
Requires-Dist: pandas-plink
Requires-Dist: requests
Requires-Dist: scikit-learn
Requires-Dist: scipy
Requires-Dist: seaborn
Requires-Dist: statsmodels
Requires-Dist: xgboost
